LICENSE
MANIFEST.in
README.rst
manage.py
pyproject.toml
requirements.txt
setup.py
./boot_django/__init__.py
./boot_django/boot_django.py
./db/__init__.py
./db/errors.py
./db/models.py
./db/query.py
./db/migrations/0001_initial.py
./db/migrations/0002_initial.py
./db/migrations/0003_teammember_delete_signupreferrer.py
./db/migrations/0004_billingaccountserver_webhookkey_workspacecredentials.py
./db/migrations/0005_destination_workspacedestination.py
./db/migrations/0006_group.py
./db/migrations/0007_alter_group_unique_together_remove_group_workspace_and_more.py
./db/migrations/0008_workspaceevents_workspaceeventlogs.py
./db/migrations/0009_rename_workspaceevents_workspaceevent_and_more.py
./db/migrations/0010_rename_workspace_id_workspaceevent_workspace.py
./db/migrations/0011_allplatform_credentials_platform_platformoauth2email_and_more.py
./db/migrations/0012_alter_platformoauth2_redirect_uri_platformaccount.py
./db/migrations/0013_authtoken.py
./db/migrations/0014_alter_authtoken_expire.py
./db/migrations/0015_alter_authtoken_expire.py
./db/migrations/0016_alter_authtoken_expire_group.py
./db/migrations/0017_alter_workspace_options_alter_authtoken_expire.py
./db/migrations/__init__.py
./ei_signals/__init__.py
./ei_signals/asgi.py
./ei_signals/log.py
./ei_signals/settings.py
./ei_signals/urls.py
./ei_signals/wsgi.py
./frontend/__init__.py
./frontend/admin.py
./frontend/apps.py
./frontend/models.py
./frontend/tests.py
./frontend/urls.py
./frontend/views.py
./frontend/migrations/__init__.py
./user/__init__.py
./user/_verify_shopify_token.py
./user/auth.py
./user/models.py
./user/shopifyAuthMiddleware.py
./user/migrations/0001_initial.py
./user/migrations/0002_alter_user_shopify_user.py
./user/migrations/0003_alter_user_is_active_alter_user_is_staff.py
./user/migrations/__init__.py
./v1/__init__.py
./v1/_group.py
./v1/credentials.py
./v1/errors.py
./v1/event.py
./v1/google_login.py
./v1/models.py
./v1/otp_login.py
./v1/platform.py
./v1/shopify_login.py
./v1/team.py
ei_signals.egg-info/PKG-INFO
ei_signals.egg-info/SOURCES.txt
ei_signals.egg-info/dependency_links.txt
ei_signals.egg-info/requires.txt
ei_signals.egg-info/top_level.txt
