Metadata-Version: 1.2
Name: ei-signals
Version: 1.0.0
Summary: EI Activation Backend
Home-page: UNKNOWN
Author: easyinsights
Author-email: support@easyinsights.ai
License: UNKNOWN
Platform: UNKNOWN
Requires-Python: >=3.9
